asynctodon/__init__.py
asynctodon/base.py
asynctodon/client.py
asynctodon/enums.py
asynctodon/errors.py
asynctodon/objects.py
asynctodon/py.typed
asynctodon/api/__init__.py
asynctodon/api/accounts.py
asynctodon/api/admin.py
asynctodon/api/apps.py
asynctodon/api/base.py
asynctodon/api/filters.py
asynctodon/api/instances.py
asynctodon/api/lists.py
asynctodon/api/misc.py
asynctodon/api/notifications.py
asynctodon/api/statuses.py
asynctodon/api/streams.py
asynctodon/api/tags.py
asynctodon/api/timelines.py
asynctodon-0.1.6.dist-info/licenses/LICENSE
asynctodon-0.1.6.dist-info/METADATA
asynctodon-0.1.6.dist-info/WHEEL
asynctodon-0.1.6.dist-info/top_level.txt
asynctodon-0.1.6.dist-info/RECORD
